CHANGES.rst
DESCRIPTION.rst
LICENSE
MANIFEST.in
README.md
setup.py
src/wai/spectralio/__init__.py
src/wai/spectralio/adams.py
src/wai/spectralio/api.py
src/wai/spectralio/arff.py
src/wai/spectralio/asc.py
src/wai/spectralio/asciixy.py
src/wai/spectralio/cal.py
src/wai/spectralio/csv.py
src/wai/spectralio/dpt.py
src/wai/spectralio/mps.py
src/wai/spectralio/nir.py
src/wai/spectralio/opus.py
src/wai/spectralio/opus_ext.py
src/wai/spectralio/spa.py
src/wai/spectralio/foss/_ConstituentValues.py
src/wai/spectralio/foss/_DataBlock.py
src/wai/spectralio/foss/_FossFile.py
src/wai/spectralio/foss/_GeneralHeader.py
src/wai/spectralio/foss/_InstrumentHeader.py
src/wai/spectralio/foss/_SampleHeader.py
src/wai/spectralio/foss/_SampleInfo.py
src/wai/spectralio/foss/__init__.py
src/wai/spectralio/foss/serialisers/_ConstituentValuesSerialiser.py
src/wai/spectralio/foss/serialisers/_DataBlockSerialiser.py
src/wai/spectralio/foss/serialisers/_DateSerialiser.py
src/wai/spectralio/foss/serialisers/_FossFileSerialiser.py
src/wai/spectralio/foss/serialisers/_GeneralHeaderSerialiser.py
src/wai/spectralio/foss/serialisers/_InstrumentHeaderSerialiser.py
src/wai/spectralio/foss/serialisers/_SafeStringSerialiser.py
src/wai/spectralio/foss/serialisers/_SampleHeaderSerialiser.py
src/wai/spectralio/foss/serialisers/_SampleInfoSerialiser.py
src/wai/spectralio/foss/serialisers/__init__.py
src/wai/spectralio/mixins/_LocaleOptionsMixin.py
src/wai/spectralio/mixins/_ProductCodeOptionsMixin.py
src/wai/spectralio/mixins/__init__.py
src/wai/spectralio/options/_Option.py
src/wai/spectralio/options/_OptionHandler.py
src/wai/spectralio/options/__init__.py
src/wai/spectralio/opus_ext_utils/_Block.py
src/wai/spectralio/opus_ext_utils/_BlockDefinition.py
src/wai/spectralio/opus_ext_utils/_CommandLineData.py
src/wai/spectralio/opus_ext_utils/__init__.py
src/wai/spectralio/opus_ext_utils/_helper.py
src/wai/spectralio/opus_ext_utils/constants.py
src/wai/spectralio/sampleidextraction/_SampleIDExtraction.py
src/wai_spectralio.egg-info/PKG-INFO
src/wai_spectralio.egg-info/SOURCES.txt
src/wai_spectralio.egg-info/dependency_links.txt
src/wai_spectralio.egg-info/requires.txt
src/wai_spectralio.egg-info/top_level.txt