Metadata-Version: 2.1
Name: wai-spectralio
Version: 0.0.5
Summary: Python library for reading/writing various NIR, MIR, XRF spectroscopy data formats.
Home-page: https://github.com/waikato-datamining/wai-spectralio
Author: Peter Reutemann
Author-email: fracpete@waikato.ac.nz
License: MIT License
Classifier: Development Status :: 4 - Beta
Classifier: License :: OSI Approved :: MIT License
Classifier: Topic :: Scientific/Engineering :: Mathematics
Classifier: Programming Language :: Python :: 3
License-File: LICENSE
